bluebild/__init__.py
bluebild/utils.py
bluebild-0.0.2.dist-info/LICENSE
bluebild-0.0.2.dist-info/METADATA
bluebild-0.0.2.dist-info/WHEEL
bluebild-0.0.2.dist-info/top_level.txt
bluebild-0.0.2.dist-info/RECORD
