Metadata-Version: 2.1
Name: bluebild
Version: 0.0.2
Summary: A flexible spherical imager for interferometric applications
Home-page: https://github.com/imagingofthings/pypeline
Author: orliac
Author-email: etienne.orliac@epfl.ch
License: UNKNOWN
Project-URL: Fork, https://github.com/etolley/pypeline
Platform: UNKNOWN
Classifier: Programming Language :: Python :: 3
Classifier: License :: OSI Approved :: MIT License
Classifier: Operating System :: OS Independent
Requires-Python: >=3.6
License-File: LICENSE
